route53_to_cloudformation.py
route53_to_cloudformation-1.0.0.dist-info/DESCRIPTION.rst
route53_to_cloudformation-1.0.0.dist-info/METADATA
route53_to_cloudformation-1.0.0.dist-info/RECORD
route53_to_cloudformation-1.0.0.dist-info/WHEEL
route53_to_cloudformation-1.0.0.dist-info/entry_points.txt
route53_to_cloudformation-1.0.0.dist-info/metadata.json
route53_to_cloudformation-1.0.0.dist-info/top_level.txt
