Metadata-Version: 2.0
Name: route53-to-cloudformation
Version: 1.0.0
Summary: Dump an existing Route53 Hosted Zone as a CloudFormation YAML template
Home-page: https://github.com/timeoutdigital/route53-to-cloudformation
Author: Adam Johnson
Author-email: me@adamj.eu
License: ISC License
Keywords: aws,cloudformation,route53
Platform: UNKNOWN
Classifier: Development Status :: 5 - Production/Stable
Classifier: Environment :: Console
Classifier: Environment :: Web Environment
Classifier: Intended Audience :: Developers
Classifier: License :: OSI Approved :: ISC License (ISCL)
Classifier: Natural Language :: English
Classifier: Operating System :: OS Independent
Classifier: Programming Language :: Python
Classifier: Programming Language :: Python :: 2
Classifier: Programming Language :: Python :: 2.7
Classifier: Programming Language :: Python :: 3
Classifier: Programming Language :: Python :: 3.6
Classifier: Topic :: Utilities
Requires-Dist: PyYAML
Requires-Dist: boto3 (>=1.4.0)
Requires-Dist: six
